nornir_network_backup/__init__.py
nornir_network_backup/cli.py
nornir_network_backup/nornir/__init__.py
nornir_network_backup/nornir/backup.py
nornir_network_backup/nornir/config.py
nornir_network_backup/nornir/plugins/__init__.py
nornir_network_backup/nornir/plugins/inventory/__init__.py
nornir_network_backup/nornir/plugins/inventory/nmap_discovery.py
nornir_network_backup/nornir/plugins/inventory/transform_functions.py
nornir_network_backup/nornir/plugins/processors/__init__.py
nornir_network_backup/nornir/plugins/processors/backup_reporter.py
nornir_network_backup/nornir/utils.py
nornir_network_backup-0.1.1.dist-info/entry_points.txt
nornir_network_backup-0.1.1.dist-info/METADATA
nornir_network_backup-0.1.1.dist-info/WHEEL
nornir_network_backup-0.1.1.dist-info/RECORD
