Metadata-Version: 2.1
Name: nornir-network-backup
Version: 0.1.1
Summary: 
Author: mwallraf
Author-email: maarten.wallraf@orange.com
Requires-Python: >=3.9,<4.0
Classifier: Programming Language :: Python :: 3
Classifier: Programming Language :: Python :: 3.9
Classifier: Programming Language :: Python :: 3.10
Classifier: Programming Language :: Python :: 3.11
Requires-Dist: click (>=8.1.3,<9.0.0)
Requires-Dist: nornir (>=3.3.0,<4.0.0)
Requires-Dist: nornir-netmiko (>=0.2.0,<0.3.0)
Requires-Dist: nornir-utils (>=0.2.0,<0.3.0)
